document_mcp/__init__.py
document_mcp/doc_tool_server.py
document_mcp/error_handler.py
document_mcp/exceptions.py
document_mcp/helpers.py
document_mcp/logger_config.py
document_mcp/mcp_client.py
document_mcp/metrics_config.py
document_mcp/config/__init__.py
document_mcp/config/settings.py
document_mcp/models/__init__.py
document_mcp/models/analysis.py
document_mcp/models/content.py
document_mcp/models/core.py
document_mcp/models/documents.py
document_mcp/tools/__init__.py
document_mcp/tools/chapter_tools.py
document_mcp/tools/content_tools.py
document_mcp/tools/document_tools.py
document_mcp/tools/paragraph_tools.py
document_mcp/tools/safety_tools.py
document_mcp/utils/__init__.py
document_mcp/utils/decorators.py
document_mcp/utils/embedding_cache.py
document_mcp/utils/file_operations.py
document_mcp/utils/validation.py
document_mcp-0.0.4.dist-info/licenses/LICENSE
document_mcp-0.0.4.dist-info/METADATA
document_mcp-0.0.4.dist-info/WHEEL
document_mcp-0.0.4.dist-info/entry_points.txt
document_mcp-0.0.4.dist-info/top_level.txt
document_mcp-0.0.4.dist-info/RECORD
