Metadata-Version: 2.4
Name: document-mcp
Version: 0.0.4
Summary: A MCP server for managing structured Markdown documents
Author: clchinkc
License-Expression: MIT
Project-URL: Homepage, https://github.com/document-mcp/document-mcp
Project-URL: Bug Tracker, https://github.com/document-mcp/document-mcp/issues
Keywords: mcp,document,management
Classifier: Programming Language :: Python :: 3
Classifier: Operating System :: OS Independent
Requires-Python: >=3.10
License-File: LICENSE
Requires-Dist: mcp[cli]>=1.0.0
Requires-Dist: python-dotenv>=1.0.0
Requires-Dist: fastapi>=0.95.0
Requires-Dist: uvicorn[standard]>=0.21.0
Requires-Dist: pydantic-ai>=0.0.14
Requires-Dist: google-generativeai>=0.8.3
Requires-Dist: openai
Requires-Dist: numpy>=1.24.0
Requires-Dist: requests>=2.28.0
Requires-Dist: prometheus-client>=0.17.0
Requires-Dist: opentelemetry-api>=1.21.0
Requires-Dist: opentelemetry-sdk>=1.21.0
Requires-Dist: opentelemetry-instrumentation>=0.42b0
Requires-Dist: opentelemetry-exporter-prometheus>=0.55b0
Requires-Dist: opentelemetry-exporter-otlp-proto-grpc>=1.35.0
Requires-Dist: opentelemetry-instrumentation-fastapi>=0.42b0
Requires-Dist: opentelemetry-instrumentation-requests>=0.42b0
Requires-Dist: python-snappy>=0.7.3
Provides-Extra: dev
Requires-Dist: pytest>=7.3.0; extra == "dev"
Requires-Dist: pytest-asyncio>=0.21.0; extra == "dev"
Requires-Dist: pytest-cov>=4.0.0; extra == "dev"
Requires-Dist: pytest-mock>=3.10.0; extra == "dev"
Requires-Dist: pytest-env>=0.5.2; extra == "dev"
Requires-Dist: pytest-xdist>=3.7.0; extra == "dev"
Requires-Dist: pytest-timeout>=2.1.0; extra == "dev"
Requires-Dist: pytest-benchmark>=4.0.0; extra == "dev"
Requires-Dist: ruff>=0.1.0; extra == "dev"
Requires-Dist: mypy>=1.0.0; extra == "dev"
Requires-Dist: memory-profiler>=0.60.0; extra == "dev"
Requires-Dist: psutil>=5.9.0; extra == "dev"
Dynamic: license-file
